mlframe/__init__.py
mlframe/load_then_test.py
mlframe/mlframe.py
mlframe/test.py
mlframe-0.1.15.dist-info/DESCRIPTION.rst
mlframe-0.1.15.dist-info/METADATA
mlframe-0.1.15.dist-info/RECORD
mlframe-0.1.15.dist-info/WHEEL
mlframe-0.1.15.dist-info/metadata.json
mlframe-0.1.15.dist-info/top_level.txt
